odoo/addons/stock_request_bom/README.rst
odoo/addons/stock_request_bom/__init__.py
odoo/addons/stock_request_bom/__manifest__.py
odoo/addons/stock_request_bom/i18n/it.po
odoo/addons/stock_request_bom/i18n/stock_request_bom.pot
odoo/addons/stock_request_bom/i18n/tr.po
odoo/addons/stock_request_bom/models/__init__.py
odoo/addons/stock_request_bom/models/stock_request_order.py
odoo/addons/stock_request_bom/readme/CONTRIBUTORS.md
odoo/addons/stock_request_bom/readme/DESCRIPTION.md
odoo/addons/stock_request_bom/readme/USAGE.md
odoo/addons/stock_request_bom/static/description/icon.png
odoo/addons/stock_request_bom/static/description/index.html
odoo/addons/stock_request_bom/tests/__init__.py
odoo/addons/stock_request_bom/tests/test_stock_request_bom.py
odoo/addons/stock_request_bom/views/stock_request_order_views.xml
odoo_addon_stock_request_bom-18.0.1.0.1.2.dist-info/METADATA
odoo_addon_stock_request_bom-18.0.1.0.1.2.dist-info/WHEEL
odoo_addon_stock_request_bom-18.0.1.0.1.2.dist-info/top_level.txt
odoo_addon_stock_request_bom-18.0.1.0.1.2.dist-info/RECORD
